arules/__init__.py
arules/association_rules.py
arules/utils/__init__.py
arules/utils/binning.py
arules/utils/selection.py
arules/utils/tests/__init__.py
arules/utils/tests/test_binning.py
arules/utils/tests/test_selection.py
tests/__init__.py
tests/association_rules/__init__.py
tests/association_rules/test_association_rules.py
arules-0.0.0.dist-info/LICENSE
arules-0.0.0.dist-info/METADATA
arules-0.0.0.dist-info/WHEEL
arules-0.0.0.dist-info/top_level.txt
arules-0.0.0.dist-info/RECORD
