Metadata-Version: 2.1
Name: arules
Version: 0.0.0
Summary: multi-purpose association rules analysis
Home-page: https://github.com/windward-ltd/arules
Author: Abir Koren
Author-email: abir@wnwd.com
License: MIT
Platform: UNKNOWN
Classifier: Development Status :: 3 - Alpha
Classifier: License :: OSI Approved :: MIT License
Classifier: Programming Language :: Python
Classifier: Programming Language :: Python :: 3.6
Classifier: Programming Language :: Python :: 3.7
Classifier: Programming Language :: Python :: 3.8
Classifier: Topic :: Software Development :: Libraries
Classifier: Topic :: Software Development :: Libraries :: Python Modules
Classifier: Intended Audience :: Developers
Requires-Python: >=3.6
Requires-Dist: pandas
Requires-Dist: numpy
